ali2b_cli_scrapper/__init__.py
ali2b_cli_scrapper/__main__.py
ali2b_cli_scrapper/app.py
ali2b_cli_scrapper/engine_and_database.py
ali2b_cli_scrapper/html_to_disk.py
ali2b_cli_scrapper/info_message.py
ali2b_cli_scrapper/models.py
ali2b_cli_scrapper/scrape_from_disk.py
ali2b_cli_scrapper/utils_scrapping.py
ali2b_cli_scrapper/web_scrapper.py
COPYING
ali2b_cli_scrapper-1.0.1.dist-info/COPYING
ali2b_cli_scrapper-1.0.1.dist-info/entry_points.txt
ali2b_cli_scrapper-1.0.1.dist-info/METADATA
ali2b_cli_scrapper-1.0.1.dist-info/WHEEL
ali2b_cli_scrapper-1.0.1.dist-info/RECORD
