Metadata-Version: 2.1
Name: ali2b-cli-scrapper
Version: 1.0.1
Summary: Scrappe all products and theirs related suppliers existing on Alibaba based on keywords provided by user and save results into a database (Mysql/Sqlite).
Home-page: https://github.com/poneoneo/Alibaba-CLI-Scrapper
License: GNU GENERAL PUBLIC LICENSEVersion 3, 29 June 2007
Keywords: cli,scrapping,alibaba,scrapper,alibaba-cli-scrapper
Author: poneoneo
Author-email: onealzero@gmail.com
Requires-Python: >=3.7,<4.0
Classifier: Development Status :: 1 - Planning
Classifier: Environment :: Console
Classifier: Framework :: AsyncIO
Classifier: Intended Audience :: Developers
Classifier: Intended Audience :: Science/Research
Classifier: License :: OSI Approved :: GNU Lesser General Public License v3 (LGPLv3)
Classifier: License :: Other/Proprietary License
Classifier: Natural Language :: English
Classifier: Operating System :: Microsoft :: Windows :: Windows 10
Classifier: Programming Language :: Python :: 3
Classifier: Programming Language :: Python :: 3.7
Classifier: Programming Language :: Python :: 3.8
Classifier: Programming Language :: Python :: 3.9
Classifier: Programming Language :: Python :: 3.10
Classifier: Programming Language :: Python :: 3.11
Classifier: Programming Language :: Python :: 3.12
Classifier: Topic :: Scientific/Engineering :: Information Analysis
Classifier: Topic :: Terminals
Classifier: Typing :: Typed
Requires-Dist: aiohttp (==3.9.5) ; python_version >= "3.8"
Requires-Dist: aiosignal (==1.3.1) ; python_version >= "3.7"
Requires-Dist: annotated-types (==0.7.0) ; python_version >= "3.8"
Requires-Dist: attrs (==23.2.0) ; python_version >= "3.7"
Requires-Dist: black (==24.4.2) ; python_version >= "3.8"
Requires-Dist: cffi (==1.16.0) ; platform_python_implementation != "PyPy"
Requires-Dist: click (==8.1.7) ; python_version >= "3.7"
Requires-Dist: colorama (==0.4.6) ; sys_platform == "win32"
Requires-Dist: cryptography (==42.0.7) ; python_version >= "3.7"
Requires-Dist: frozenlist (==1.4.1) ; python_version >= "3.8"
Requires-Dist: greenlet (==3.0.3) ; platform_machine == "aarch64" or platform_machine == "ppc64le" or platform_machine == "x86_64" or platform_machine == "amd64" or platform_machine == "AMD64" or platform_machine == "win32" or platform_machine == "WIN32"
Requires-Dist: idna (==3.7) ; python_version >= "3.5"
Requires-Dist: loguru (==0.7.2) ; python_version >= "3.5"
Requires-Dist: markdown-it-py (==3.0.0) ; python_version >= "3.8"
Requires-Dist: mdurl (==0.1.2) ; python_version >= "3.7"
Requires-Dist: multidict (==6.0.5) ; python_version >= "3.7"
Requires-Dist: mypy-extensions (==1.0.0) ; python_version >= "3.5"
Requires-Dist: mysqlclient (==2.2.4) ; python_version >= "3.8"
Requires-Dist: nodeenv (==1.9.1) ; python_version >= "2.7" and python_version not in "3.0, 3.1, 3.2, 3.3, 3.4, 3.5, 3.6"
Requires-Dist: packaging (==24.0) ; python_version >= "3.7"
Requires-Dist: pathspec (==0.12.1) ; python_version >= "3.8"
Requires-Dist: platformdirs (==4.2.2) ; python_version >= "3.8"
Requires-Dist: playwright (==1.44.0) ; python_version >= "3.8"
Requires-Dist: pycparser (==2.22) ; python_version >= "3.8"
Requires-Dist: pydantic (==2.7.3) ; python_version >= "3.8"
Requires-Dist: pydantic-core (==2.18.4) ; python_version >= "3.8"
Requires-Dist: pyee (==11.1.0) ; python_version >= "3.8"
Requires-Dist: pygments (==2.18.0) ; python_version >= "3.8"
Requires-Dist: pyright (==1.1.365) ; python_version >= "3.7"
Requires-Dist: python-decouple (==3.8)
Requires-Dist: python-dotenv (==1.0.1) ; python_version >= "3.8"
Requires-Dist: rich (==13.7.1) ; python_full_version >= "3.7.0"
Requires-Dist: selectolax (==0.3.21)
Requires-Dist: shellingham (==1.5.4) ; python_version >= "3.7"
Requires-Dist: sqlalchemy (==2.0.30) ; python_version >= "3.7"
Requires-Dist: sqlmodel (==0.0.19) ; python_version >= "3.7"
Requires-Dist: typer (==0.12.3) ; python_version >= "3.7"
Requires-Dist: typing-extensions (==4.12.1) ; python_version >= "3.8"
Requires-Dist: win32-setctime (==1.1.0) ; sys_platform == "win32"
Requires-Dist: yarl (==1.9.4) ; python_version >= "3.7"
Project-URL: Repository, https://github.com/poneoneo/Alibaba-CLI-Scrapper
